{
  "id": "d13ec396-5ca3-4ae5-8451-3442765c5abb",
  "prevId": "301ac579-5843-4fa3-8b30-6012ab5546da",
  "version": "7",
  "dialect": "postgresql",
  "tables": {
    "public.geese": {
      "name": "geese",
      "schema": "",
      "columns": {
        "id": {
          "name": "id",
          "type": "serial",
          "primaryKey": true,
          "notNull": true
        },
        "name": {
          "name": "name",
          "type": "text",
          "primaryKey": false,
          "notNull": true
        },
        "description": {
          "name": "description",
          "type": "text",
          "primaryKey": false,
          "notNull": false
        },
        "is_leader": {
          "name": "is_leader",
          "type": "boolean",
          "primaryKey": false,
          "notNull": false
        },
        "programming_language": {
          "name": "programming_language",
          "type": "text",
          "primaryKey": false,
          "notNull": false
        },
        "motivations": {
          "name": "motivations",
          "type": "jsonb",
          "primaryKey": false,
          "notNull": false
        },
        "location": {
          "name": "location",
          "type": "text",
          "primaryKey": false,
          "notNull": false
        },
        "bio": {
          "name": "bio",
          "type": "text",
          "primaryKey": false,
          "notNull": false
        },
        "avatar": {
          "name": "avatar",
          "type": "text",
          "primaryKey": false,
          "notNull": false
        },
        "honks": {
          "name": "honks",
          "type": "integer",
          "primaryKey": false,
          "notNull": false,
          "default": 0
        },
        "created_at": {
          "name": "created_at",
          "type": "timestamp",
          "primaryKey": false,
          "notNull": true,
          "default": "now()"
        },
        "updated_at": {
          "name": "updated_at",
          "type": "timestamp",
          "primaryKey": false,
          "notNull": true,
          "default": "now()"
        }
      },
      "indexes": {},
      "foreignKeys": {},
      "compositePrimaryKeys": {},
      "uniqueConstraints": {}
    }
  },
  "enums": {},
  "schemas": {},
  "sequences": {},
  "_meta": {
    "columns": {},
    "schemas": {},
    "tables": {}
  }
}